ImbalancedLearningRegression/__init__.py
ImbalancedLearningRegression/adasyn.py
ImbalancedLearningRegression/box_plot_stats.py
ImbalancedLearningRegression/cnn.py
ImbalancedLearningRegression/dist_metrics.py
ImbalancedLearningRegression/enn.py
ImbalancedLearningRegression/gn.py
ImbalancedLearningRegression/over_sampling_adasyn.py
ImbalancedLearningRegression/over_sampling_gn.py
ImbalancedLearningRegression/over_sampling_ro.py
ImbalancedLearningRegression/over_sampling_smote.py
ImbalancedLearningRegression/phi.py
ImbalancedLearningRegression/phi_ctrl_pts.py
ImbalancedLearningRegression/random_under.py
ImbalancedLearningRegression/ro.py
ImbalancedLearningRegression/smote.py
ImbalancedLearningRegression/tomeklinks.py
ImbalancedLearningRegression/under_sampling_cnn.py
ImbalancedLearningRegression/under_sampling_enn.py
ImbalancedLearningRegression/under_sampling_random.py
ImbalancedLearningRegression/under_sampling_tomeklinks.py
ImbalancedLearningRegression-0.0.1.dist-info/LICENSE
ImbalancedLearningRegression-0.0.1.dist-info/METADATA
ImbalancedLearningRegression-0.0.1.dist-info/WHEEL
ImbalancedLearningRegression-0.0.1.dist-info/top_level.txt
ImbalancedLearningRegression-0.0.1.dist-info/RECORD
