Metadata-Version: 2.1
Name: ImbalancedLearningRegression
Version: 0.0.1
Summary: Python implementations of preprocesssing imbalanced data for regression
Home-page: https://github.com/paobranco/ImbalancedLearningRegression
Author: Paula Branco, Wenglei Wu, Alex Chengen Lyu, Lingyi Kong, Gloria Hu
Author-email: pbranco@uottawa.ca, wwu077@uottawa.ca, clyu039@uottawa.ca, lkong073@uottawa.ca, xhu005@uottawa.ca
License: UNKNOWN
Keywords: smote,Gaussian noise,condensed nearest neighbour,edited nearest neighbour,Tomek links,ADASYN,over-sampling,under-sampling,synthetic data,imbalanced data,pre-processing,regression
Platform: UNKNOWN
Classifier: Programming Language :: Python :: 3
Classifier: Intended Audience :: Developers
Classifier: Intended Audience :: Science/Research
Classifier: Intended Audience :: Education
Classifier: Topic :: Scientific/Engineering
Classifier: Topic :: Scientific/Engineering :: Mathematics
Classifier: Topic :: Scientific/Engineering :: Artificial Intelligence
Classifier: License :: OSI Approved :: GNU General Public License v3 (GPLv3)
License-File: LICENSE
Requires-Dist: numpy
Requires-Dist: pandas
Requires-Dist: tqdm
Requires-Dist: sklearn
